faster_whisper/__init__.py
faster_whisper/audio.py
faster_whisper/feature_extractor.py
faster_whisper/tokenizer.py
faster_whisper/transcribe.py
faster_whisper/utils.py
faster_whisper/vad.py
faster_whisper/version.py
faster_whisper/assets/__init__.py
faster_whisper/assets/silero_decoder_v5.onnx
faster_whisper/assets/silero_encoder_v5.onnx
unhallucinated_faster_whisper-1.0.3.dist-info/LICENSE
unhallucinated_faster_whisper-1.0.3.dist-info/METADATA
unhallucinated_faster_whisper-1.0.3.dist-info/WHEEL
unhallucinated_faster_whisper-1.0.3.dist-info/top_level.txt
unhallucinated_faster_whisper-1.0.3.dist-info/RECORD
