Metadata-Version: 2.2
Name: unhallucinated_faster_whisper
Version: 1.0.3
Summary: Faster Whisper transcription with CTranslate2
Home-page: https://github.com/SYSTRAN/faster-whisper
Author: Guillaume Klein
License: MIT
Keywords: openai whisper speech ctranslate2 inference quantization transformer
Classifier: Development Status :: 4 - Beta
Classifier: Intended Audience :: Developers
Classifier: Intended Audience :: Science/Research
Classifier: License :: OSI Approved :: MIT License
Classifier: Programming Language :: Python :: 3
Classifier: Programming Language :: Python :: 3 :: Only
Classifier: Programming Language :: Python :: 3.8
Classifier: Programming Language :: Python :: 3.9
Classifier: Programming Language :: Python :: 3.10
Classifier: Programming Language :: Python :: 3.11
Classifier: Topic :: Scientific/Engineering :: Artificial Intelligence
Requires-Python: >=3.8
License-File: LICENSE
Requires-Dist: ctranslate2<5,>=4.0
Requires-Dist: huggingface_hub>=0.13
Requires-Dist: tokenizers<1,>=0.13
Requires-Dist: onnxruntime<2,>=1.14
Requires-Dist: torch>=2.1.1
Requires-Dist: av>=11
Requires-Dist: tqdm
Provides-Extra: conversion
Requires-Dist: transformers[torch]>=4.23; extra == "conversion"
Provides-Extra: dev
Requires-Dist: black==23.*; extra == "dev"
Requires-Dist: flake8==6.*; extra == "dev"
Requires-Dist: isort==5.*; extra == "dev"
Requires-Dist: pytest==7.*; extra == "dev"
Dynamic: author
Dynamic: classifier
Dynamic: description
Dynamic: description-content-type
Dynamic: home-page
Dynamic: keywords
Dynamic: license
Dynamic: provides-extra
Dynamic: requires-dist
Dynamic: requires-python
Dynamic: summary
